tcpflow/__init__.py
tcpflow/tcpflow.py
tcpflow-0.1.1.dist-info/DESCRIPTION.rst
tcpflow-0.1.1.dist-info/METADATA
tcpflow-0.1.1.dist-info/RECORD
tcpflow-0.1.1.dist-info/WHEEL
tcpflow-0.1.1.dist-info/metadata.json
tcpflow-0.1.1.dist-info/top_level.txt
